setup.cfg
setup.py
pyautobrightness/__init__.py
pyautobrightness/pyautobrightness.py
pyautobrightness/pyautobrightnessmain.py
pyautobrightness.egg-info/PKG-INFO
pyautobrightness.egg-info/SOURCES.txt
pyautobrightness.egg-info/dependency_links.txt
pyautobrightness.egg-info/entry_points.txt
pyautobrightness.egg-info/top_level.txt