Metadata-Version: 1.1
Name: pyautobrightness
Version: 0.2.2
Summary: A very simple software to change the screen brightness using a webcam as light sensor.
Home-page: https://github.com/evertonstz/py-auto-brightness
Author: Everton Correia
Author-email: evertonjcorreia@gmail.com
License: GPL
Download-URL: https://github.com/evertonstz/py-auto-brightness/tarball/0.2.2
Keywords: Brightness,Auto,Webcam
Platform: Unix
